nonebot_plugin_bingimagecreator/__init__.py
nonebot_plugin_bingimagecreator/config.py
nonebot_plugin_bingimagecreator/generator.py
nonebot_plugin_bingimagecreator-0.1.5.dist-info/WHEEL
nonebot_plugin_bingimagecreator-0.1.5.dist-info/METADATA
nonebot_plugin_bingimagecreator-0.1.5.dist-info/RECORD
