Metadata-Version: 2.1
Name: nonebot-plugin-bingimagecreator
Version: 0.1.5
Summary: A nonebot plugin for Bing DALL-E 3
License: MIT
Author: Alpaca
Author-email: alpaca@bupt.edu.cn
Requires-Python: >=3.8,<4.0
Classifier: License :: OSI Approved :: MIT License
Classifier: Programming Language :: Python :: 3
Classifier: Programming Language :: Python :: 3.8
Classifier: Programming Language :: Python :: 3.9
Classifier: Programming Language :: Python :: 3.10
Classifier: Programming Language :: Python :: 3.11
Requires-Dist: asyncio (>=3.4.3,<4.0.0)
Requires-Dist: fake_useragent (>=1.4.0,<2.0.0)
Requires-Dist: nonebot-adapter-onebot (>=2.2.1,<3.0.0)
Requires-Dist: nonebot2 (>=2.0.0rc3,<3.0.0)
